LICENSE.txt
README.md
setup.cfg
setup.py
odefinterp.egg-info/PKG-INFO
odefinterp.egg-info/SOURCES.txt
odefinterp.egg-info/dependency_links.txt
odefinterp.egg-info/requires.txt
odefinterp.egg-info/top_level.txt
odeformer/__init__.py
odeformer/logger.py
odeformer/metrics.py
odeformer/optim.py
odeformer/regressors.py
odeformer/slurm.py
odeformer/trainer.py
odeformer/utils.py
odeformer/baselines/__init__.py
odeformer/baselines/baseline_utils.py
odeformer/baselines/ellyn_wrapper.py
odeformer/baselines/ffx_wrapper.py
odeformer/baselines/proged_wrapper.py
odeformer/baselines/pysr_wrapper.py
odeformer/baselines/sindy_wrapper.py
odeformer/envs/__init__.py
odeformer/envs/encoders.py
odeformer/envs/environment.py
odeformer/envs/generators.py
odeformer/envs/simplifiers.py
odeformer/envs/utils.py
odeformer/model/__init__.py
odeformer/model/embedders.py
odeformer/model/mixins.py
odeformer/model/model_wrapper.py
odeformer/model/sklearn_wrapper.py
odeformer/model/transformer.py
odeformer/model/utils_wrapper.py
odeformer/odebench/__init__.py
odeformer/odebench/solve_and_plot.py
odeformer/odebench/strogatz_equations.py